infnum/__init__.py
infnum-0.2.0.dist-info/METADATA
infnum-0.2.0.dist-info/WHEEL
infnum-0.2.0.dist-info/RECORD
