Metadata-Version: 2.3
Name: infnum
Version: 0.2.0
Summary: Infinite and infinitesimal numbers for JAX
Author-email: Alok Singh <alokbeniwal@gmail.com>
Requires-Python: >=3.12
Requires-Dist: jax>=0.4.35
Requires-Dist: jaxlib>=0.4.35
Requires-Dist: jaxtyping>=0.2.34
